backtrader_binance_futures/__init__.py
backtrader_binance_futures/binance_broker.py
backtrader_binance_futures/binance_feed.py
backtrader_binance_futures/binance_store.py
backtrader_binance_futures-2.0.5.dist-info/LICENSE
backtrader_binance_futures-2.0.5.dist-info/METADATA
backtrader_binance_futures-2.0.5.dist-info/WHEEL
backtrader_binance_futures-2.0.5.dist-info/top_level.txt
backtrader_binance_futures-2.0.5.dist-info/RECORD
